setup.py
shinkenplugins/__init__.py
shinkenplugins.plugins.http2.egg-info/PKG-INFO
shinkenplugins.plugins.http2.egg-info/SOURCES.txt
shinkenplugins.plugins.http2.egg-info/dependency_links.txt
shinkenplugins.plugins.http2.egg-info/entry_points.txt
shinkenplugins.plugins.http2.egg-info/namespace_packages.txt
shinkenplugins.plugins.http2.egg-info/pbr.json
shinkenplugins.plugins.http2.egg-info/requires.txt
shinkenplugins.plugins.http2.egg-info/top_level.txt
shinkenplugins/plugins/__init__.py
shinkenplugins/plugins/http2/__init__.py
shinkenplugins/plugins/http2/http2.py